terminal_velocity/__init__.py
terminal_velocity/git.py
terminal_velocity/notebook.py
terminal_velocity/terminal_velocity.py
terminal_velocity/urwid_ui.py
terminal_velocity_git-0.2.0.dist-info/DESCRIPTION.rst
terminal_velocity_git-0.2.0.dist-info/METADATA
terminal_velocity_git-0.2.0.dist-info/RECORD
terminal_velocity_git-0.2.0.dist-info/WHEEL
terminal_velocity_git-0.2.0.dist-info/entry_points.txt
terminal_velocity_git-0.2.0.dist-info/metadata.json
terminal_velocity_git-0.2.0.dist-info/top_level.txt
