Metadata-Version: 2.0
Name: terminal-velocity-git
Version: 0.2.0
Summary: A fast note-taking app for the UNIX terminal, with Git support.
Home-page: https://github.com/jongracecox/terminal_velocity
Author: Sean Hammond, Vincent Perricone, Jon Grace-Cox
Author-email: UNKNOWN
License: GNU General Public License, Version 3
Platform: UNKNOWN
Classifier: Programming Language :: Python :: 2
Classifier: Programming Language :: Python :: 2 :: Only
Classifier: Programming Language :: Python :: 2.6
Classifier: Programming Language :: Python :: 2.7
Requires-Dist: urwid (>=1.1.1)
Requires-Dist: chardet (>=2.1.1)
Requires-Dist: sh (>=1.12.14)
Requires-Dist: PyYAML (>=3.1.2)
